ctx_i18n.py
ctx_i18n-0.1.2.dist-info/METADATA
ctx_i18n-0.1.2.dist-info/WHEEL
ctx_i18n-0.1.2.dist-info/RECORD
