Metadata-Version: 2.4
Name: ctx-i18n
Version: 0.1.2
Summary: Context-aware internationalization utility for Python
License: MIT
Requires-Python: >=3.14
Classifier: License :: OSI Approved :: MIT License
Classifier: Programming Language :: Python :: 3
Classifier: Programming Language :: Python :: 3.14
Requires-Dist: jq-utils (>=0.1.1,<0.2.0)
Requires-Dist: pyyaml (>=6.0.3,<7.0.0)
